lychorhyce/__init__.py
lychorhyce/lcr.py
lychorhyce/lychorhyce.html.j2
lychorhyce/lychorhyce.py
lychorhyce-1.0.0.dist-info/entry_points.txt
lychorhyce-1.0.0.dist-info/LICENSE.md
lychorhyce-1.0.0.dist-info/WHEEL
lychorhyce-1.0.0.dist-info/METADATA
lychorhyce-1.0.0.dist-info/RECORD
