Metadata-Version: 2.1
Name: lychorhyce
Version: 1.0.0
Summary: Create lyrics + chords + rhythm song files from LCR text files.
Home-page: https://lcr4songs.readthedocs.io/
License: GPL-3.0-only
Author: Nicola 'tekNico' Larosa
Author-email: coding@teknico.net
Maintainer: Nicola 'tekNico' Larosa
Maintainer-email: coding@teknico.net
Requires-Python: >=3.7,<4.0
Classifier: Development Status :: 4 - Beta
Classifier: Environment :: Console
Classifier: License :: OSI Approved :: GNU General Public License v3 (GPLv3)
Classifier: Natural Language :: English
Classifier: Operating System :: OS Independent
Classifier: Programming Language :: Python :: 3
Classifier: Programming Language :: Python :: 3.7
Classifier: Programming Language :: Python :: 3.8
Classifier: Programming Language :: Python :: 3.9
Classifier: Topic :: Artistic Software
Classifier: Topic :: Text Processing :: Markup
Requires-Dist: Jinja2 (>=2.11.3,<3.0.0)
Requires-Dist: importlib-metadata (>=3.10.0,<4.0.0)
Project-URL: Documentation, https://lcr4songs.readthedocs.io/
Project-URL: Repository, https://hg.sr.ht/~teknico/lcr4songs
